{
    "muito": 2.5,
    "mt": 1.5,
    "super": 2.0,
    "demais": 1.8,
    "bastante": 1.4,
    "extremamente": 2.5,
    "absolutamente": 2.2,
    "completamente": 2.0,
    "totalmente": 1.8,
    "perfeitamente": 2.0,
    "excepcionalmente": 2.3,
    "incredivelmente": 2.4,
    "extraordinariamente": 2.5,
    "fantasticamente": 2.2,
    "maravilhosamente": 2.3,
    "tremendamente": 1.8,
    "enormemente": 1.9,
    "massivamente": 1.7,
    "intensamente": 1.6,
    "profundamente": 1.5,
    "realmente": 1.3,
    "verdadeiramente": 1.4,
    "genuinamente": 1.4,
    "genuamente": 1.4,
    "terrivelmente": -2.0,
    "horrivelmente": -2.2,
    "desesperadamente": -1.8,
    "ligeiramente": 1.2,
    "levemente": 1.2,
    "um_pouco": 1.2,
    "um pouco": 1.2,
    "pouquinho": 1.1,
    "pouco": 0.8,
    "nem um pouco": 0.4,
    "nada de": 0.4,
    "dificilmente": 0.7,
    "raramente": 0.8,
    "escassa": 0.6,
    "mal": 0.7,
    "malmente": 0.6,
    "não": -0.5,
    "nao": -0.5,
    "nenhum": -0.7,
    "nenhuma": -0.7,
    "jamais": -0.8,
    "nunca": -0.8,
    "quase": 1.0,
    "meio": 1.0,
    "nada": 0.1,
    "nem": -0.02,
    "máximo": 2.0,
    "mínimo": 0.5,
    "máxima": 2.0,
    "mínima": 0.5,
    "altamente": 2.1,
    "baixamente": 0.6,
    "sempre": 1.8,
    "constantemente": 1.6,
    "frequentemente": 1.4,
    "ocasionalmente": 1.1,
    "esporadicamente": 1.0,
    "periodicamente": 1.2,
    "diariamente": 1.5,
    "semanalmente": 1.3,
    "mensalmente": 1.1,
    "anualmente": 1.0,
    "imediatamente": 2.2,
    "instantaneamente": 2.3,
    "rapidamente": 1.8,
    "lentamente": 0.7,
    "gradualmente": 1.0,
    "suavemente": 1.2,
    "brutalmente": -2.1,
    "violentamente": -2.3,
    "agressivamente": -1.9,
    "calmamente": 1.3,
    "pacificamente": 1.4,
    "tranquilamente": 1.3,
    "serenamente": 1.4,
    "dramaticamente": 1.9,
    "radicalmente": 2.0,
    "drasticamente": 2.1,
    "significativamente": 1.7,
    "substancialmente": 1.6,
    "consideravelmente": 1.5,
    "notavelmente": 1.6,
    "visivelmente": 1.4,
    "obviamente": 1.5,
    "evidentemente": 1.5,
    "claramente": 1.4,
    "distintamente": 1.3,
    "precisamente": 1.6,
    "exatamente": 1.7,
    "aproximadamente": 1.2,
    "basicamente": 1.3,
    "fundamentalmente": 1.4,
    "essencialmente": 1.4,
    "principalmente": 1.3,
    "especialmente": 1.5,
    "particularmente": 1.4,
    "especificamente": 1.4,
    "geralmente": 1.2,
    "normalmente": 1.1,
    "comumente": 1.1,
    "tipicamente": 1.2,
    "habitualmente": 1.2,
    "rotineiramente": 1.1,
    "regularmente": 1.2,
    "irregularmente": 0.8,
    "eternamente": 2.0,
    "permanentemente": 1.7,
    "temporariamente": 1.0,
    "provisoriamente": 1.0,
    "definitivamente": 1.8,
    "certamente": 1.6,
    "seguramente": 1.5,
    "possivelmente": 1.1,
    "provavelmente": 1.2,
    "talvez": 1.0,
    "eventualmente": 1.1,
    "finalmente": 1.3,
    "ultimamente": 1.2,
    "recentemente": 1.1,
    "atualmente": 1.1,
    "presentemente": 1.1,
    "hoje": 1.2,
    "ontem": 1.0,
    "amanhã": 1.2,
    "agora": 1.3,
    "já": 1.2,
    "ainda": 1.1,
    "também": 1.1,
    "só": 1.0,
    "apenas": 1.0,
    "somente": 1.0,
    "exclusivamente": 1.4,
    "inclusivamente": 1.3,
    "máximos": 2.0,
    "mínimos": 0.5,
    "máximas": 2.0,
    "mínimas": 0.5
}
